{
   "xAxis" : {
      "type" : "category"
   },
   "chart" : {
      "type" : "column"
   },
   "title" : {
      "text" : "The Weekly Challenge - 119"
   },
   "series" : [
      {
         "data" : [
            {
               "name" : "Abigail",
               "y" : 22,
               "drilldown" : "Abigail"
            },
            {
               "name" : "Dave Jacoby",
               "drilldown" : "Dave Jacoby",
               "y" : 2
            },
            {
               "drilldown" : "Eric Cheung",
               "y" : 2,
               "name" : "Eric Cheung"
            },
            {
               "name" : "Frank Oosterhuis",
               "drilldown" : "Frank Oosterhuis",
               "y" : 2
            },
            {
               "y" : 2,
               "drilldown" : "Gabor Szabo",
               "name" : "Gabor Szabo"
            },
            {
               "y" : 4,
               "drilldown" : "James Smith",
               "name" : "James Smith"
            },
            {
               "name" : "Lance Wicks",
               "y" : 1,
               "drilldown" : "Lance Wicks"
            },
            {
               "name" : "Lucas Ransan",
               "drilldown" : "Lucas Ransan",
               "y" : 2
            },
            {
               "drilldown" : "Mohammad Meraj Zia",
               "y" : 1,
               "name" : "Mohammad Meraj Zia"
            },
            {
               "name" : "Paulo Custodio",
               "y" : 20,
               "drilldown" : "Paulo Custodio"
            },
            {
               "name" : "Roger Bell_West",
               "y" : 6,
               "drilldown" : "Roger Bell_West"
            },
            {
               "drilldown" : "Steven Wilson",
               "y" : 2,
               "name" : "Steven Wilson"
            },
            {
               "name" : "Stuart Little",
               "y" : 6,
               "drilldown" : "Stuart Little"
            },
            {
               "y" : 1,
               "drilldown" : "Ulrich Rieke",
               "name" : "Ulrich Rieke"
            }
         ],
         "colorByPoint" : "true",
         "name" : "The Weekly Challenge Guest Contributions"
      }
   ],
   "plotOptions" : {
      "series" : {
         "dataLabels" : {
            "enabled" : 1,
            "format" : "{point.y}"
         },
         "borderWidth" : 0
      }
   },
   "drilldown" : {
      "series" : [
         {
            "id" : "Abigail",
            "name" : "Abigail",
            "data" : [
               [
                  "Awk",
                  2
               ],
               [
                  "Bash",
                  2
               ],
               [
                  "Bc",
                  1
               ],
               [
                  "Befunge",
                  1
               ],
               [
                  "C",
                  2
               ],
               [
                  "Go",
                  1
               ],
               [
                  "Java",
                  1
               ],
               [
                  "Lua",
                  2
               ],
               [
                  "Node.js",
                  2
               ],
               [
                  "Pascal",
                  1
               ],
               [
                  "Python",
                  2
               ],
               [
                  "R",
                  1
               ],
               [
                  "Ruby",
                  2
               ],
               [
                  "Scheme",
                  1
               ],
               [
                  "Tcl",
                  1
               ]
            ]
         },
         {
            "id" : "Dave Jacoby",
            "name" : "Dave Jacoby",
            "data" : [
               [
                  "Node.js",
                  2
               ]
            ]
         },
         {
            "data" : [
               [
                  "Excel VBA",
                  2
               ]
            ],
            "name" : "Eric Cheung",
            "id" : "Eric Cheung"
         },
         {
            "data" : [
               [
                  "Scala",
                  2
               ]
            ],
            "id" : "Frank Oosterhuis",
            "name" : "Frank Oosterhuis"
         },
         {
            "data" : [
               [
                  "Crystal",
                  2
               ]
            ],
            "name" : "Gabor Szabo",
            "id" : "Gabor Szabo"
         },
         {
            "id" : "James Smith",
            "name" : "James Smith",
            "data" : [
               [
                  "CESIL",
                  1
               ],
               [
                  "JavaScript",
                  1
               ],
               [
                  "PHP",
                  1
               ],
               [
                  "Python",
                  1
               ]
            ]
         },
         {
            "name" : "Lance Wicks",
            "id" : "Lance Wicks",
            "data" : [
               [
                  "Go",
                  1
               ]
            ]
         },
         {
            "data" : [
               [
                  "Myrddin",
                  2
               ]
            ],
            "id" : "Lucas Ransan",
            "name" : "Lucas Ransan"
         },
         {
            "id" : "Mohammad Meraj Zia",
            "name" : "Mohammad Meraj Zia",
            "data" : [
               [
                  "Java",
                  1
               ]
            ]
         },
         {
            "name" : "Paulo Custodio",
            "id" : "Paulo Custodio",
            "data" : [
               [
                  "Ada",
                  2
               ],
               [
                  "Awk",
                  2
               ],
               [
                  "Basic",
                  2
               ],
               [
                  "Bc",
                  2
               ],
               [
                  "C",
                  2
               ],
               [
                  "C++",
                  2
               ],
               [
                  "D",
                  2
               ],
               [
                  "Forth",
                  2
               ],
               [
                  "Lua",
                  2
               ],
               [
                  "Python",
                  2
               ]
            ]
         },
         {
            "name" : "Roger Bell_West",
            "id" : "Roger Bell_West",
            "data" : [
               [
                  "Python",
                  2
               ],
               [
                  "Ruby",
                  2
               ],
               [
                  "Rust",
                  2
               ]
            ]
         },
         {
            "data" : [
               [
                  "Python",
                  2
               ]
            ],
            "id" : "Steven Wilson",
            "name" : "Steven Wilson"
         },
         {
            "data" : [
               [
                  "Haskell",
                  2
               ],
               [
                  "Node.js",
                  2
               ],
               [
                  "Python",
                  2
               ]
            ],
            "id" : "Stuart Little",
            "name" : "Stuart Little"
         },
         {
            "data" : [
               [
                  "C++",
                  1
               ]
            ],
            "name" : "Ulrich Rieke",
            "id" : "Ulrich Rieke"
         }
      ]
   },
   "yAxis" : {
      "title" : {
         "text" : "Total Solutions"
      }
   },
   "subtitle" : {
      "text" : "[Guests: 14]. Click the columns to drilldown the contributions breakdown. Last updated at 2021-07-04 13:55:48 GMT"
   },
   "tooltip" : {
      "headerFormat" : "<span style=\"font-size:11px\"></span>",
      "followPointer" : "true",
      "pointFormat" : "<span style=\"color:{point.color}\">{point.name}</span>: <b>{point.y:f}</b><br/>"
   },
   "legend" : {
      "enabled" : "false"
   }
}
