{
  "slug":    "review-challenge-158",
  "title":   "Colin Crain › Perl Weekly Review #158",
  "author":  "Colin Crain",
  "date":    "2 May 2022",
  "image":   "https://theweeklychallenge.org/images/blog/p5-review-challenge-158.jpg",
  "content": "\n( *...continues from [previous week](/blog/review-challenge-157/).* )\n\nWelcome to the Perl review pages for **Week 158** of The Weekly Challenge! Here we will take the time to discuss the  submissions offered up by the team, factor out some common methodologies that came up in those solutions, and highlight some of the unique approaches and unusual code created.\n\n---\n\n### ●︎ Why do we do these challenges?\n\nI suppose any reasonable answer to that question would be from a field as wide ranging and varied as the people who choose to join the team. One thing, though, is clear: it's not a competition, and there are no judges, even if there is a \"prize\" of sorts. About that -- I think of it more as an honorarium periodically awarded to acknowledge the efforts we make towards this strange goal. So there's no determination to find the *fastest*, or the *shortest*, or even, in some abstract way, the *best* way to go about things, although I'm certain the participants have their own aspirations and personal drives. As Perl is such a wonderfully expressive language, this provides quite a bit of fodder to the core idea of TMTOWTDI, producing a gamut of varied techniques and solutions.\n\nEven the tasks themselves are often open to a certain amount of discretionary interpretation. What we end up with is a situation where each participant is producing something in the manner they find the most interesting or satisfying. Some team members focus on carefully crafted complete applications, thoroughly vetting input data and handling every use case they can think up. Others choose to apply themselves to the logic of the underlying puzzle and making it work in the most elegant way they can. Some eschew modules they would ordinarily reach for, others embrace them, bringing to light wheels perhaps invented years ago that happen to exactly solve the problem in front of them today.\n\nI've been considering this question for some time and have found one binding commonality between all of us out solving these challenges each week, in that however we normally live our lives, the task in front of us more than likely has nothing to do with any of that. And I think this has great value. We all do what we do, in the real world, and hopefully we do it well. The Weekly Challenge provides us with an opportunity to do something germane to that life yet distinctly different; if we only do the things we already know how to do then we will only do the same things over and over. This is where the \"challenge\" aspect comes into play.\n\nSo we can consider The Weekly Challenge as providing a problem space outside of our comfort zone, as far out from that comfort as we wish to take things. From those reaches we can gather and learn things, pick and choose and bring what we want back into our lives. Personally, I think that's what this whole thing is about. YMMV.\n\n---\n\nEvery week there is an enormous global collective effort made by the team, analyzing and creatively coding the submissions, and that effort deserves credit due.\n\nAnd that, my friends, is why I'm here, to try and figure out ways to do just that.\n\nSo, here we are then. I'm ready — let’s get to it and see what we can find.\n\n---\n\n### For Additional Context…\n\nbefore we begin, you may wish to revisit either the pages for the [**original tasks**](/blog/perl-weekly-challenge-158/) or the summary [**recap**](/blog/recap-challenge-158/) of the challenge. But don't worry about it, the challenge text will be repeated and presented as we progress from task to task.\n\nOh, and one more thing before we get started:\n\n\n### Getting in Touch with Us\n\n\n![image](https://theweeklychallenge.org/images/blog/Email.svg)\n Email › Please feel free to email me (Colin) with any feedback, notes, clarifications or whatnot about this review.\n\n\n![image](https://theweeklychallenge.org/images/blog/Github.svg)\n GitHub › Submit a pull request to us for any issues you may find with this page.\n\n\n![image](https://theweeklychallenge.org/images/blog/Twitter.svg)\n Twitter › Join the discussion on Twitter!\n\nI'm always curious as to what the people think of these efforts. Everyone here at the PWC would like to hear any feedback you'd like to give.\n\n...So finally, without further ado...\n\n---\n\n## •   \u0026nbsp;  \u0026nbsp;  \u0026nbsp;   [Task 1](#PWC158TASK1)       \u0026nbsp;  \u0026nbsp;  \u0026nbsp;   •   \u0026nbsp;  \u0026nbsp;  \u0026nbsp;   [Task 2](#PWC158TASK2)   \u0026nbsp;  \u0026nbsp;  \u0026nbsp;   \t•   \u0026nbsp;  \u0026nbsp;  \u0026nbsp;   [BLOGS](#PWC158BLOGS)    \u0026nbsp;  \u0026nbsp;  \u0026nbsp;   \t•\n\n---\n\n---\n\n# TASK 1 {#PWC158TASK1}\n\n# Additive Primes\n*Submitted by: Mohammad S Anwar*\n\nWrite a script to find out all Additive Primes  1);\n\n        # Generate a table of primes sufficient\n        # for our purposes\n        my $prime_table = ${sieve_of_eratosthenes($n, 1)};\n        my @additives;\n\n        # Loop over the range from 2 to $n\n        for my $i (2 .. $n){\n            my $sum = 0;\n\n            # Skip numbers that aren't prime\n            next\n                unless(substr($prime_table, $i, 1));\n\n            # Loop over each digit of $i and\n            # sum them\n            foreach(split('', $i)){\n                $sum += $_;\n            }\n\n            # If the sum is prime, add $i to\n            # the list\n            push(@additives, $i)\n                if(substr($prime_table, $sum, 1));\n\n        }\n\n        # Return the list of additive primes\n        return(@additives);\n\n    }\n```\n\n[**Jorg Sommrey**](https://github.com/manwar/perlweeklychallenge-club/blob/master/challenge-158/jo-37/perl/ch-1.pl)\n\nIn contrast to Matthew's piec-by-piece construction from base materials, Jorg assembles a hero's collection of high-level components to craft a tight and elegant machine for the task.\n\nFrom the number theory module `Math::Prime:Util` Jorg selects four functions: `prime_iterator`, `is_prime`, `vecsum`, and `todigits`. Working backwards from the end of that list:\n* `todigits` is a generalized function to split a number into an array of digits, with the added property of being able to convert that number into any requested base before the split. Because of this Jorg's approach will also be able to find additive primes in any base.\n* The `vecsum` function works my like `sum0` from `List::Util`, but assumes the input array is integers and avoids any floating-point math.\n* `is_prime` does what it says, returning an up/down boolean condition as 1 and 0\n* `prime_iterator` returns a coderef closed around a prime number generator, and is initialized to a given number, defaulting to 2. When this coderef is called, the next sequential prime number is returned, and cannot be reset.\n\nThe additive prime logic is run as a coroutine, using `Coro::Generator`. A coroutine is comparable to a subroutine that preserves state, that one can step in and out of as directed. The `gather` and `take` control structure borrowed from Raku completes the machine, collecting values returned from the coroutine into an anonymous array until the conditions have been fulfilled, and then returning the list.\n\nBecause the base for the digit-summation in this implementation can be varied, setting it to binary produces the [pernicious primes](https://theweeklychallenge.org/blog/perl-weekly-challenge-156/#TASK1). Ain't number theory grand?\n\n```perl\n    use Math::Prime::Util qw(prime_iterator is_prime vecsum todigits);\n    use Coro::Generator;\n    use Syntax::Keyword::Gather;\n\n    ### Input and Output\n    say for additive_primes_below(shift, $base);\n\n    ### Implementation\n    sub additive_primes_below ($limit, $base = 10) {\n        my $p_i = prime_iterator();\n\n        # Build a generator for additive primes in the given base.\n        my $ap_i = generator {\n            my $p;\n            while () {\n                yield $p if is_prime vecsum todigits $p = $p_i-\u003e(), $base;\n            }\n        };\n\n        # Collect all additive primes below the given limit.\n        gather {\n            my $ap;\n            take $ap while ($ap = $ap_i-\u003e())  0 ) {\n        push(@outarr, $i);\n      }\n\n      $i++;\n    }\n```\n\n\n[**Pete Houston**](https://github.com/manwar/perlweeklychallenge-club/blob/master/challenge-158/pete-houston/perl/ch-1.pl)\n\nUsing external module functions the process can be remarkably compact. Here Pete demonstrates just how compact that can be.\n\n```perl\n    use List::Util qw/sum/;\n    use Math::Prime::Util qw/is_prime primes/;\n\n    say join ', ', grep { is_prime (sum split //) } @{primes (100)};\n```\n\n[**Bruce Gray**](https://github.com/manwar/perlweeklychallenge-club/blob/master/challenge-158/bruce-gray/perl/ch-1a.sh)\n\n\u0026nbsp;\u0026nbsp;**additional languages:**\n[Go](https://github.com/manwar/perlweeklychallenge-club/blob/master/challenge-158/bruce-gray/go/ch-1.go), [Raku](https://github.com/manwar/perlweeklychallenge-club/blob/master/challenge-158/bruce-gray/raku/ch-1.raku)\n\nBruce gives him a run for the money with his equally concise solution. I'm not going to count characters. You get the idea.\n\nIn a side note, of course `Math::Prime::Util` has a `sumdigits` function. What self-respecting number theory package would not? With a little over 200 functions and constants available, its easy to lose one or two, and there always seems to be another way of doing something.\n\n```perl\n    use ntheory qw;\n    my @r = grep { is_prime sumdigits $_ } @{ primes(100) };\n\n    say join ', ', @r;\n```\n\n\n[**Roger Bell_West**](https://github.com/manwar/perlweeklychallenge-club/blob/master/challenge-158/roger-bell-west/perl/ch-1.pl)\n\n\u0026nbsp;\u0026nbsp;**additional languages:**\n[Javascript](https://github.com/manwar/perlweeklychallenge-club/blob/master/challenge-158/roger-bell-west/javascript/ch-1.js), [Kotlin](https://github.com/manwar/perlweeklychallenge-club/blob/master/challenge-158/roger-bell-west/kotlin/ch-1.kt), [Lua](https://github.com/manwar/perlweeklychallenge-club/blob/master/challenge-158/roger-bell-west/lua/ch-1.lua), [Postscript](https://github.com/manwar/perlweeklychallenge-club/blob/master/challenge-158/roger-bell-west/postscript/ch-1.ps), [Python](https://github.com/manwar/perlweeklychallenge-club/blob/master/challenge-158/roger-bell-west/python/ch-1.py), [Raku](https://github.com/manwar/perlweeklychallenge-club/blob/master/challenge-158/roger-bell-west/raku/ch-1.p6), [Ruby](https://github.com/manwar/perlweeklychallenge-club/blob/master/challenge-158/roger-bell-west/ruby/ch-1.rb), [Rust](https://github.com/manwar/perlweeklychallenge-club/blob/master/challenge-158/roger-bell-west/rust/ch-1.rs)\n\n\n\u0026nbsp;\u0026nbsp;**blog writeup:**\n[RogerBW's Blog: The Weekly Challenge 158: Prime Cuban Additives](https://blog.firedrake.org/archive/2022/03/The_Weekly_Challenge_158__Prime_Cuban_Additives.html)\n\nRoger dusts off his `genprimes` routine, which finds all primes up to a given value using the [6*k*±1 scheme](https://en.wikipedia.org/wiki/Primality_test#Simple_methods), which reduces trial division by a factor of three. Primes in hand, the digits are summed by dividing down modulo 10, which as we learned from James' experiments is perhaps the fastest way to do this. So good on Roger there.\n\nAs any positive number's digit sum will be less than the value itself, when the primes are examined as candidates they are then placed into a hash to lookup the compounded value.\n\n```perl\n    sub genprimes {\n      my $mx=shift;\n      my @primes;\n      {\n        my %primesh=map {$_ =\u003e 1} (2,3);\n        for (my $i=6;$i  $b} keys %primesh;\n      }\n      return \\@primes;\n    }\n\n    sub digitsum {\n      my $s=0;\n      my $x=shift;\n      while ($x \u003e 0) {\n        $s += $x % 10;\n        $x = int($x/10);\n      }\n      return $s;\n    }\n\n    sub additiveprimes {\n      my $mx=shift;\n      my @o;\n      my %ps;\n      foreach my $q (@{genprimes($mx)}) {\n        $ps{$q}=1;\n        if (exists $ps{digitsum($q)}) {\n          push @o,$q;\n        }\n      }\n      return \\@o;\n    }\n```\n\n[**Peter Campbell Smith**](https://github.com/manwar/perlweeklychallenge-club/blob/master/challenge-158/peter-campbell-smith/perl/ch-1.pl)\n\n\n\u0026nbsp;\u0026nbsp;**blog writeup:**\n[All about primes](https://pjcs-pwc.blogspot.com/2022/03/all-about-primes.html)\n\nAnd finally, here's something new: because we know the range required for the calculations, Peter unrolls the digit summing into a one-line formula adding up the number mod 10, the number over 10 mod 10, and the number over 100 mod 10. This expansion of the loop will actually work  for all numbers up to 999 of course; 991 is the largest additive prime in that range, summing to 19.\n\n```perl\n    use Math::Prime::Util 'is_prime';\n    my ($j, $s);\n\n    for $j (1 .. 100) {\n        next unless is_prime($j);\n        $s = $j % 10 + int($j / 10) % 10 + int($j / 100) % 10;\n        say qq[$j is an additive prime whose digits sum to $s] if is_prime($s);\n    }\n```\n\n\n## Blogs and Additional Submissions in Guest Languages for Task 1:\n\n\n[**Ali Moradi**](https://github.com/manwar/perlweeklychallenge-club/blob/master/challenge-158/deadmarshal/perl/ch-1.pl)\n\n\u0026nbsp;\u0026nbsp;**additional languages:**\n[Lua](https://github.com/manwar/perlweeklychallenge-club/blob/master/challenge-158/deadmarshal/lua/ch-1.lua), [Pascal](https://github.com/manwar/perlweeklychallenge-club/blob/master/challenge-158/deadmarshal/pascal/ch1.pas)\n\n\n[**Arne Sommer**](https://github.com/manwar/perlweeklychallenge-club/blob/master/challenge-158/arne-sommer/perl/ch-1.pl)\n\n\u0026nbsp;\u0026nbsp;**additional languages:**\n[Raku](https://github.com/manwar/perlweeklychallenge-club/blob/master/challenge-158/arne-sommer/raku/ch-1.raku)\n\n\n\u0026nbsp;\u0026nbsp;**blog writeup:**\n[Cuban Addition, Primarily with Raku](https://raku-musings.com/cuban-addition.html)\n\n\n[**Athanasius**](https://github.com/manwar/perlweeklychallenge-club/blob/master/challenge-158/athanasius/perl/ch-1.pl)\n\n\u0026nbsp;\u0026nbsp;**additional languages:**\n[Raku](https://github.com/manwar/perlweeklychallenge-club/blob/master/challenge-158/athanasius/raku/ch-1.raku)\n\n\n[**Colin Crain**](https://github.com/manwar/perlweeklychallenge-club/blob/master/challenge-158/colin-crain/perl/ch-1.pl)\n\n\u0026nbsp;\u0026nbsp;**additional languages:**\n[Raku](https://github.com/manwar/perlweeklychallenge-club/blob/master/challenge-158/colin-crain/raku/ch-1.raku)\n\n\n\u0026nbsp;\u0026nbsp;**blog writeup:**\n[Add Another Prime to the Pile - Programming Excursions in Perl and Raku](https://colincrain.com/2022/04/03/add-another-prime-to-the-pile)\n\n\n\n[**Dave Jacoby**](https://github.com/manwar/perlweeklychallenge-club/blob/master/challenge-158/dave-jacoby/perl/ch-1.pl)\n\n\n\u0026nbsp;\u0026nbsp;**blog writeup:**\n[In Our Primes: Weekly Challenge #158 | Committed to Memory](https://jacoby.github.io/2022/03/28/in-our-primes-weekly-challenge-158.html)\n\n\n[**Flavio Poletti**](https://github.com/manwar/perlweeklychallenge-club/blob/master/challenge-158/polettix/perl/ch-1.pl)\n\n\u0026nbsp;\u0026nbsp;**additional languages:**\n[Raku](https://github.com/manwar/perlweeklychallenge-club/blob/master/challenge-158/polettix/raku/ch-1.raku)\n\n\n\u0026nbsp;\u0026nbsp;**blog writeup:**\n[PWC158 - Additive Primes - ETOOBUSY](https://github.polettix.it/ETOOBUSY/2022/03/29/pwc158-additive-primes/)\n\n\n\n[**Jaldhar H. Vyas**](https://github.com/manwar/perlweeklychallenge-club/blob/master/challenge-158/jaldhar-h-vyas/perl/ch-1.pl)\n\n\u0026nbsp;\u0026nbsp;**additional languages:**\n[Raku](https://github.com/manwar/perlweeklychallenge-club/blob/master/challenge-158/jaldhar-h-vyas/raku/ch-1.sh)\n\n\n\u0026nbsp;\u0026nbsp;**blog writeup:**\n[Perl Weekly Challenge: Week 158](https://www.braincells.com/perl/2022/04/perl_weekly_challenge_week_158.html)\n\n\n[**Lubos Kolouch**](https://github.com/manwar/perlweeklychallenge-club/blob/master/challenge-158/lubos-kolouch/perl/ch-1.pl)\n\n\u0026nbsp;\u0026nbsp;**additional languages:**\n[Python](https://github.com/manwar/perlweeklychallenge-club/blob/master/challenge-158/lubos-kolouch/python/ch-1.py)\n\n\n[**Mohammad S Anwar**](https://github.com/manwar/perlweeklychallenge-club/blob/master/challenge-158/mohammad-anwar/perl/ch-1.pl)\n\n\u0026nbsp;\u0026nbsp;**additional languages:**\n[Raku](https://github.com/manwar/perlweeklychallenge-club/blob/master/challenge-158/mohammad-anwar/raku/ch-1.raku)\n\n\n[**PokGoPun**](https://github.com/manwar/perlweeklychallenge-club/blob/master/challenge-158/pokgopun/perl/ch-1.pl)\n\n\u0026nbsp;\u0026nbsp;**additional languages:**\n[Go](https://github.com/manwar/perlweeklychallenge-club/blob/master/challenge-158/pokgopun/go/ch-1.go)\n\n\n[**Simon Green**](https://github.com/manwar/perlweeklychallenge-club/blob/master/challenge-158/sgreen/perl/ch-1.pl)\n\n\u0026nbsp;\u0026nbsp;**additional languages:**\n[Python](https://github.com/manwar/perlweeklychallenge-club/blob/master/challenge-158/sgreen/python/ch-1.py)\n\n\n\u0026nbsp;\u0026nbsp;**blog writeup:**\n[It's a primathon!](https://dev.to/simongreennet/its-a-primathon-5aki)\n\n\n[**Ulrich Rieke**](https://github.com/manwar/perlweeklychallenge-club/blob/master/challenge-158/ulrich-rieke/perl/ch-1.pl)\n\n\u0026nbsp;\u0026nbsp;**additional languages:**\n[C++](https://github.com/manwar/perlweeklychallenge-club/blob/master/challenge-158/ulrich-rieke/cpp/ch-1.cpp), [Haskell](https://github.com/manwar/perlweeklychallenge-club/blob/master/challenge-158/ulrich-rieke/haskell/ch-1.hs), [Raku](https://github.com/manwar/perlweeklychallenge-club/blob/master/challenge-158/ulrich-rieke/raku/ch-1.raku)\n\n\n[**W. Luis Mochan**](https://github.com/manwar/perlweeklychallenge-club/blob/master/challenge-158/wlmb/perl/ch-1.pl)\n\n\n\u0026nbsp;\u0026nbsp;**blog writeup:**\n[Perl Weekly Challenge 158 – W. Luis Mochán](https://wlmb.github.io/2022/03/28/PWC158/)\n\n\n------------------------------------------\n\n\n\n\n\n---\n\n# TASK 2 {#PWC158TASK2}\n\n# First Series Cuban Primes\n*Submitted by: Mohammad S Anwar*\n\nWrite a script to compute first series Cuban Primes 3 - *y*3) / (*x* - *y*)\n\nwhere *x* = *y* + *k* for some *k*.\n\nNot all cubic differences in a given pattern will be primes, mind you, but those that do make up a given *series* of Cubam primes, with the label of the series the difference between the root values. Successive primes, 23, 33, 43, for example, have a difference of 1 and are hence called the first series Cuban primes. The divisor in the root equation, *x* - *y*, is thus 1.\n\nWhat we are looking for is thus simplified: prime numbers that can be expressed as the difference between two successive cubes.\n\nIn the second and later series, the sequence values are renormalized by dividing by the difference between the root values.\n\nThere were 27 submissions for the second task this past week.\n\n## The *Son* and the *Rhumba* — TIMTOWTDI\n[**PokGoPun**](https://github.com/manwar/perlweeklychallenge-club/blob/master/challenge-158/pokgopun/perl/ch-2.pl),\n[**Athanasius**](https://github.com/manwar/perlweeklychallenge-club/blob/master/challenge-158/athanasius/perl/ch-2.pl),\n[**Lubos Kolouch**](https://github.com/manwar/perlweeklychallenge-club/blob/master/challenge-158/lubos-kolouch/perl/ch-2.pl),\n[**Colin Crain**](https://github.com/manwar/perlweeklychallenge-club/blob/master/challenge-158/colin-crain/perl/ch-2.pl),\n[**Ali Moradi**](https://github.com/manwar/perlweeklychallenge-club/blob/master/challenge-158/deadmarshal/perl/ch-2.pl),\n[**Flavio Poletti**](https://github.com/manwar/perlweeklychallenge-club/blob/master/challenge-158/polettix/perl/ch-2.pl),\n[**Alexander Pankoff**](https://github.com/manwar/perlweeklychallenge-club/blob/master/challenge-158/alexander-pankoff/perl/ch-2.pl),\n[**W. Luis Mochan**](https://github.com/manwar/perlweeklychallenge-club/blob/master/challenge-158/wlmb/perl/ch-2.pl), and\n[**Jorg Sommrey**](https://github.com/manwar/perlweeklychallenge-club/blob/master/challenge-158/jo-37/perl/ch-2.pl)\n\nThe search for Cuban primes revolves around the collection and detection of primes and, perhaps inexplicably, the centered hexagonal figurate numbers. This connection, of course, it through the cubes that make up the definition. We ended up with quite a lot of self-similarity in the solution pool, with common method centered on creating candidate values from the defining equation — or some transformation —  and then testing them in some manner for primality.\n\n[**PokGoPun**](https://github.com/manwar/perlweeklychallenge-club/blob/master/challenge-158/pokgopun/perl/ch-2.pl)\n\n\u0026nbsp;\u0026nbsp;**additional languages:**\n[Go](https://github.com/manwar/perlweeklychallenge-club/blob/master/challenge-158/pokgopun/go/ch-2.go)\n\nWe'll start the survey with the example from noted Go enthusiast PokGoPun. A block is created around an incrementing counter, and the difference is found between the cubes of the counter and an adjacent value. Once we have this, then the result is checked for primality using `is_prime()` from `Math::Prime::Util`.\n\nOf note the defining equation is a polynomial with two variables, *x* and *y*, yet *y* is then further defined by a relationship to *x*. Consequently the initial expression can be rewritten in terms of *x*:\n\n*x*3 - (*x*-1)3 = 3*x*2 + 3*x* + 1\n\nCandidates that are found to be prime are added to a stringified output list and a `redo` statement turns the block into an infinite loop.\n\nI so much prefer this loop construct over an `while (1) {...}` or similar formation, employing a conditional that can never fail. But that's just me. It just seems more direct and to the point, instead of using what amounts to a side-effect.\n\n```perl\n    use Math::Prime::Util qw/is_prime/;\n\n    my $n = shift;\n    $n = 1000 unless $n \u0026\u0026 $n =~ /^\\d+$/;\n    my $o = \"\";\n    #my $i = 2;\n    my $i = 1;\n    {\n        #my $cp = $i**3 - ($i-1)**3;\n        my $cp = 3*$i*$i + 3*$i + 1;\n        last if $cp \u003e $n;\n        $o .= \", $cp\" if is_prime($cp);\n        $i++;\n        redo;\n    }\n    $o =~ s/^\\D+//;\n    printf \"%s\\n\", $o;\n```\n\n\n[**Athanasius**](https://github.com/manwar/perlweeklychallenge-club/blob/master/challenge-158/athanasius/perl/ch-2.pl)\n\n\u0026nbsp;\u0026nbsp;**additional languages:**\n[Raku](https://github.com/manwar/perlweeklychallenge-club/blob/master/challenge-158/athanasius/raku/ch-2.raku)\n\nThe monk brings to light that the reworked equation we saw above:\n\n\nH(n) = 3n² - 3n + 1\n\ndefines the form of the centered hexagonal number *n*. So they proceed to produce those values and then check them for primality. Only the names have been changed, to draw attention to the interesting congruence.\n\n\n```perl\n    for (my ($n, $hex_number) = (1, 0); $hex_number  $n;\n          push @primes, $p;\n        }\n      }\n      return @primes;\n    }\n\n    print \"$_ \" foreach cuban_primes(1000);\n```\n\n[**Flavio Poletti**](https://github.com/manwar/perlweeklychallenge-club/blob/master/challenge-158/polettix/perl/ch-2.pl)\n\n\u0026nbsp;\u0026nbsp;**additional languages:**\n[Raku](https://github.com/manwar/perlweeklychallenge-club/blob/master/challenge-158/polettix/raku/ch-2.raku)\n\n\n\u0026nbsp;\u0026nbsp;**blog writeup:**\n[PWC158 - First Series Cuban Primes - ETOOBUSY](https://github.polettix.it/ETOOBUSY/2022/03/30/pwc158-first-series-cuban-primes/)\n\nFlavio, using the same approach some how seems  to manage to make it even more compact.\n\nAgain, I'm not counting characters and this isn't a competition.\n\n```perl\n    use ntheory 'is_prime';\n\n    my $M = shift // 1000;\n    my @cubans;\n    my $y = 1;\n    while ((my $p = 3 * $y * ($y + 1) + 1) 3. This follows from the fact that if a given  centered hexagonal number is the difference between two sequential cubes, adding the value to the smaller cube will yield this larger. This difference, among the figurate numbers, is known as the [gnomon](https://en.wikipedia.org/wiki/Figurate_number#Gnomon). The process of reduction can then be repeated down to 1 to demonstrate the complete pattern.\n\nAlexander also chooses the centered hexagonal phrasing for the central equation.\n\n```perl\n    sub cuban_primes($max = 1000) {\n\n        my @cubans    = ();\n        my $i         = 1;\n        my $candidate = 0;\n        while ( $candidate 3 - *x*3 = N\n\nto yield an maximum result value within an upper boundary *N* of\n\nmax *k* = (-3 + √3 √(4*N* - 1)) / 6\n\nPutting these together using the range 1 to the maximum *k* produces the 17 possible values for the Cubans, 11 of which are prime.\n\n```perl\n    use Math::Prime::Util qw(is_prime);\n    die \"Usage: ./ch-2.pl N\\n\\tto find cuban primes up to N\" unless @ARGV;\n    my $N=shift;\n    die \"N should be positive\" unless $N\u003e0;\n    my $bound=(-3+sqrt(3)*sqrt(4*$N-1))/6; # Solve (x+1)^3-x^3=N\n    say \"The cuban primes up to $N are \",\n        join \", \", grep {is_prime $_} map {1+3*$_*($_+1)} (1..$bound);\n```\n\n\n\n\n[**Jorg Sommrey**](https://github.com/manwar/perlweeklychallenge-club/blob/master/challenge-158/jo-37/perl/ch-2.pl)\n\nFinally, we'll return to Jorg, who brings us another coroutine machine to study. This one makes generalized Cuban primes in any specified series that is not a multiple of 3 (as we have previously stated that these do not exist). Here the coroutine state keeps an iterator that is appied to the the equation\n\n*p* = 3*y*2 + 3*ny* + *n*2\n\nwhich can then be used to find what ends up being the gnomon between the centered hexagonal numbers:\n\n**P***y* + 1 = **P***y* + 3 (2*y* + *n* + 1)\n\nThe coroutine keeps track of the previous centered hexagonal and the index and adds the gnomon. If the result is prime, *¡Viva la Cuba!*\n\n\n\n```perl\n    use Coro::Generator;\n    use Math::Prime::Util 'is_prime';\n    use Syntax::Keyword::Gather;\n    use experimental 'signatures';\n\n    ### Input and Output\n    say for cuban_primes_below($series, shift);\n\n\n    ### Implementation\n    # Calculating generalized series of cuban primes, controlled by\n    # parameter n.  The first and second series are produced by values 1 and\n    # 2 respectively.  Restricting to y \u003e 0.\n    # The relation p = (x³ - y³) / (x - y), x = y + n can easily be\n    # transformed into\n    # p = 3 y² + 3 n y + n².\n    # A simple calculation reveals\n    # p(y + 1) = p(y) + 3 (2 y + n + 1)\n    # which gives a nice iterative formula for p starting with y = 0\n    # and p = n².\n    sub cuban_primes_below ($n, $limit) {\n        # There is no n-th series if n is a multiple of 3.\n        die 'no such series' unless $n % 3;\n\n        # Build a generator for cuban primes by checking if p is prime.\n        my $cp_i = generator {\n            my ($y, $p) = (0, $n ** 2);\n            while () {\n                $p += 3 * (2 * $y++ + $n + 1);\n                yield $p if is_prime $p;\n            }\n        };\n\n        # Collect cuban primes below the given limit.\n        gather {\n            my $cp;\n            take $cp while ($cp = $cp_i-\u003e())  \u0026nbsp; \n \u0026nbsp; \n \u0026nbsp; \n \u0026nbsp; \n\n\n_________ THE BLOG PAGES _________\n\n\n\n---\n\n**That’s it for me this week, people! Warped by the rain, driven by the snow, resolute and unbroken by the torrential influx, by some miracle I somehow continue to maintain my bearings.**\n\n**Looking forward to next wave, the perfect wave, I am: *your humble servant*.**\n\n# But if Your Unquenchable *THIRST* for *KNOWLEDGE* is not *SLAKED*, {#PWC158BLOGS}\n# then *RUN* *(dont walk!)* to the *WATERING HOLE*\n# and *FOLLOW* these *BLOG* *LINKS*:\n\n**( ...*don't think, trust your training, you're in the zone, just do it ...* )**\n\n\n**Arne Sommer**\n\n * [Cuban Addition, Primarily with Raku](https://raku-musings.com/cuban-addition.html) ( *Perl \u0026 Raku* )\n\n**Colin Crain**\n\n * [Add Another Prime to the Pile - Programming Excursions in Perl and Raku](https://colincrain.com/2022/04/03/add-another-prime-to-the-pile) ( *Perl \u0026 Raku* )\n * [Cubans In Their Prime - Programming Excursions in Perl and Raku](https://colincrain.com/2022/04/03/cubans-in-their-prime) ( *Perl \u0026 Raku* )\n\n**Dave Jacoby**\n\n * [In Our Primes: Weekly Challenge #158 | Committed to Memory](https://jacoby.github.io/2022/03/28/in-our-primes-weekly-challenge-158.html) ( *Perl* )\n\n**Flavio Poletti**\n\n * [PWC158 - Additive Primes - ETOOBUSY](https://github.polettix.it/ETOOBUSY/2022/03/29/pwc158-additive-primes/) ( *Perl \u0026 Raku* )\n * [PWC158 - First Series Cuban Primes - ETOOBUSY](https://github.polettix.it/ETOOBUSY/2022/03/30/pwc158-first-series-cuban-primes/) ( *Perl \u0026 Raku* )\n\n**Jaldhar H. Vyas**\n\n * [Perl Weekly Challenge: Week 158](https://www.braincells.com/perl/2022/04/perl_weekly_challenge_week_158.html) ( *Perl \u0026 Raku* )\n\n**James Smith**\n\n * [Perl Weekly Challenge #158](https://github.com/drbaggy/perlweeklychallenge-club/tree/master/challenge-158/james-smith) ( *Perl* )\n\n**Laurent Rosenfeld**\n\n * [Perl Weekly Challenge 158: Additive Primes and Cuban Primes](http://blogs.perl.org/users/laurent_r/2022/03/perl-weekly-challenge-158-additive-primes-and-cuban-primes.html) ( *Perl \u0026 Raku* )\n\n**Luca Ferrari**\n\n * [Perl Weekly Challenge 158: to be prime or not to be prime – Luca Ferrari – Open Source advocate, human being](https://fluca1978.github.io/2022/03/28/PerlWeeklyChallenge158.html#task1) ( *Raku* )\n * [Perl Weekly Challenge 158: to be prime or not to be prime – Luca Ferrari – Open Source advocate, human being](https://fluca1978.github.io/2022/03/28/PerlWeeklyChallenge158.html#task1plperl) ( *PL/PERL* )\n * [Perl Weekly Challenge 158: to be prime or not to be prime – Luca Ferrari – Open Source advocate, human being](https://fluca1978.github.io/2022/03/28/PerlWeeklyChallenge158.html#task1plpgsql) ( *PL/PgSQL* )\n\n**Peter Campbell Smith**\n\n * [All about primes](https://pjcs-pwc.blogspot.com/2022/03/all-about-primes.html) ( *Perl* )\n\n**Roger Bell_West**\n\n * [RogerBW's Blog: The Weekly Challenge 158: Prime Cuban Additives](https://blog.firedrake.org/archive/2022/03/The_Weekly_Challenge_158__Prime_Cuban_Additives.html) ( *Perl \u0026 Raku* )\n\n**Simon Green**\n\n * [It's a primathon!](https://dev.to/simongreennet/its-a-primathon-5aki) ( *Perl* )\n\n**W. Luis Mochan**\n\n * [Perl Weekly Challenge 158 – W. Luis Mochán](https://wlmb.github.io/2022/03/28/PWC158/) ( *Perl* )\n"
}
